ip_debug
