Metadata-Version: 2.1
Name: django-ip-debug
Version: 0.1.5
Summary: Middleware que habilita DEBUG solo para IPs Autorizadas en Proyectos Django
Home-page: https://github.com/oguerrero/django-ip-debug
Download-URL: https://github.com/oguerrerog/django-ip-debug/archive/refs/tags/v0.1.5.tar.gz
Author: Oscar Guerrero G.
Author-email: oguerrerog@gmail.com
License: MIT license
Keywords: debug django
Classifier: Development Status :: 4 - Beta
Classifier: Environment :: Web Environment
Classifier: Framework :: Django
Classifier: Intended Audience :: Developers
Classifier: License :: OSI Approved :: MIT License
Classifier: Natural Language :: Spanish
Classifier: Programming Language :: Python :: 3.9
Classifier: Topic :: Software Development :: Libraries
Requires-Python: >=3.9
License-File: LICENSE
Requires-Dist: Django>=4.2
Requires-Dist: ipaddress
